testcontainers_bowerick/__init__.py
testcontainers_bowerick/bowerick.py
testcontainers_bowerick-0.1.0.dist-info/LICENSE.txt
testcontainers_bowerick-0.1.0.dist-info/METADATA
testcontainers_bowerick-0.1.0.dist-info/WHEEL
testcontainers_bowerick-0.1.0.dist-info/top_level.txt
testcontainers_bowerick-0.1.0.dist-info/RECORD
